README.md
setup.py
mobile_modem_exporter/mobile_modem_exporter.py
mobile_modem_exporter/test_mobile_modem_exporter.py
mobile_modem_exporter.egg-info/PKG-INFO
mobile_modem_exporter.egg-info/SOURCES.txt
mobile_modem_exporter.egg-info/dependency_links.txt
mobile_modem_exporter.egg-info/entry_points.txt
mobile_modem_exporter.egg-info/requires.txt
mobile_modem_exporter.egg-info/top_level.txt