Metadata-Version: 2.1
Name: mobile-modem-exporter
Version: 0.1.0
Summary: mobile_modem_exporter is a Prometheus exporter for mobile modems. It uses pySerial and pexpect to speak to the modems and prometheus_client to write to node_exporter textfile_collector path.
Home-page: https://github.com/tykling/mobile_modem_exporter
Author: Thomas Steen Rasmussen
Author-email: thomas@gibfest.dk
License: BSD License
Platform: UNKNOWN
Classifier: Programming Language :: Python :: 3.7
Classifier: Programming Language :: Python :: 3.8
Classifier: License :: OSI Approved :: BSD License
Classifier: Operating System :: OS Independent
Requires-Python: >=3.7
